autofixpy/__init__.py
autofixpy/cli.py
autofixpy/core.py
autofixpy-1.0.0.dist-info/LICENSE
autofixpy-1.0.0.dist-info/METADATA
autofixpy-1.0.0.dist-info/WHEEL
autofixpy-1.0.0.dist-info/entry_points.txt
autofixpy-1.0.0.dist-info/top_level.txt
autofixpy-1.0.0.dist-info/RECORD
